adme_py/__init__.py
adme_py/adme.py
adme_py/bbb_coords.tsv
adme_py/druglikeness.py
adme_py/hia_coords.tsv
adme_py/input_handlers.py
adme_py/lipophilicity.py
adme_py/medicinal.py
adme_py/pharmacokinetics.py
adme_py/physiochemical.py
adme_py/solubility.py
adme_py-0.1.0.dist-info/METADATA
adme_py-0.1.0.dist-info/WHEEL
adme_py-0.1.0.dist-info/licenses/LICENSE
adme_py-0.1.0.dist-info/RECORD
