Metadata-Version: 2.3
Name: adme-py
Version: 0.1.0
Summary: Tool to calculate ADME properties in python.
Project-URL: Homepage, https://github.com/mcnaughtonadm/adme-py
Project-URL: Repository, https://github.com/mcnaughtonadm/adme-py.git
Project-URL: Issues, https://github.com/mcnaughtonadm/adme-py/issues
Author-email: Andrew McNaughton <mcnaughtonadm@gmail.com>
Maintainer-email: Andrew McNaughton <mcnaughtonadm@gmail.com>
License: MIT License
License-File: LICENSE
Keywords: adme,cheminformatics
Classifier: Development Status :: 3 - Alpha
Classifier: License :: OSI Approved :: BSD License
Classifier: Programming Language :: Python :: 3.8
Classifier: Programming Language :: Python :: 3.9
Classifier: Programming Language :: Python :: 3.10
Classifier: Programming Language :: Python :: 3.11
Requires-Python: >=3.8
Requires-Dist: matplotlib>=3.9.2
Requires-Dist: pandas>=2.2.2
Requires-Dist: rdkit>=2023.9.6
